CHANGELOG.md
LICENSE
MANIFEST.in
Makefile
README.md
setup.cfg
setup.py
tox.ini
tests/test_token_expiration.py
tests/test_user_token_connections.py
tests/test_user_token_device_registry.py
tests/test_user_token_flow.py
tests/test_user_token_registry.py
wc_django_jwt.egg-info/PKG-INFO
wc_django_jwt.egg-info/SOURCES.txt
wc_django_jwt.egg-info/dependency_links.txt
wc_django_jwt.egg-info/requires.txt
wc_django_jwt.egg-info/top_level.txt
wcd_jwt/__init__.py
wcd_jwt/apps.py
wcd_jwt/authentication.py
wcd_jwt/conf.py
wcd_jwt/discovery.py
wcd_jwt/exceptions.py
wcd_jwt/middleware.py
wcd_jwt/resolver.py
wcd_jwt/serializers.py
wcd_jwt/signals.py
wcd_jwt/subscriptions.py
wcd_jwt/utils.py
wcd_jwt/views.py
wcd_jwt/contrib/__init__.py
wcd_jwt/contrib/device_registry/__init__.py
wcd_jwt/contrib/device_registry/admin.py
wcd_jwt/contrib/device_registry/apps.py
wcd_jwt/contrib/device_registry/models.py
wcd_jwt/contrib/device_registry/signals.py
wcd_jwt/contrib/device_registry/migrations/0001_initial.py
wcd_jwt/contrib/device_registry/migrations/__init__.py
wcd_jwt/contrib/device_registry/services/__init__.py
wcd_jwt/contrib/device_registry/services/connector.py
wcd_jwt/contrib/device_registry/services/pipeline.py
wcd_jwt/contrib/jet/__init__.py
wcd_jwt/contrib/jet/admin.py
wcd_jwt/contrib/jet/apps.py
wcd_jwt/contrib/registry/__init__.py
wcd_jwt/contrib/registry/admin.py
wcd_jwt/contrib/registry/apps.py
wcd_jwt/contrib/registry/authentication.py
wcd_jwt/contrib/registry/conf.py
wcd_jwt/contrib/registry/models.py
wcd_jwt/contrib/registry/serializers.py
wcd_jwt/contrib/registry/signals.py
wcd_jwt/contrib/registry/subscriptions.py
wcd_jwt/contrib/registry/utils.py
wcd_jwt/contrib/registry/views.py
wcd_jwt/contrib/registry/migrations/0001_initial.py
wcd_jwt/contrib/registry/migrations/0002_token_internal_expired_at.py
wcd_jwt/contrib/registry/migrations/__init__.py
wcd_jwt/contrib/registry/services/__init__.py
wcd_jwt/contrib/registry/services/archiver.py
wcd_jwt/contrib/registry/services/pipeline.py
wcd_jwt/contrib/registry/services/token_manager.py
wcd_jwt/contrib/registry/services/user_connector.py
wcd_jwt/locale/af/LC_MESSAGES/django.mo
